dj_rest_admin/__init__.py
dj_rest_admin/apps.py
dj_rest_admin/decorators.py
dj_rest_admin/restmodeladmin.py
dj_rest_admin/sites.py
dj_rest_admin/migrations/__init__.py
dj_rest_admin-1.0.2.dist-info/LICENSE
dj_rest_admin-1.0.2.dist-info/METADATA
dj_rest_admin-1.0.2.dist-info/WHEEL
dj_rest_admin-1.0.2.dist-info/top_level.txt
dj_rest_admin-1.0.2.dist-info/RECORD
