Metadata-Version: 2.1
Name: dj-rest-admin
Version: 1.0.2
Summary: A package to generate CRUD endpoints for registered models with the Django-REST Framework.
Author-email: Dario Fragas <dariofg98@gmail.com>
License: MIT License
Project-URL: Homepage, https://github.com/dfg-98/dj-rest-admin
Keywords: django,python,django-rest-framework,admin,api
Classifier: License :: OSI Approved :: MIT License
Classifier: Programming Language :: Python :: 3
Classifier: Programming Language :: Python :: 3.8
Classifier: Intended Audience :: Developers
Classifier: Topic :: Software Development :: Build Tools
Requires-Python: >=3.8
License-File: LICENSE
Requires-Dist: django (>=3.2)
Requires-Dist: djangorestframework (>=3.13)
Provides-Extra: dev
Requires-Dist: black ; extra == 'dev'
Requires-Dist: bumpver ; extra == 'dev'
Requires-Dist: isort ; extra == 'dev'
Requires-Dist: pip-tools ; extra == 'dev'
Requires-Dist: pytest ; extra == 'dev'
Requires-Dist: coverage ; extra == 'dev'
